setup.cfg
setup.py
playstore/__init__.py
playstore.egg-info/PKG-INFO
playstore.egg-info/SOURCES.txt
playstore.egg-info/dependency_links.txt
playstore.egg-info/entry_points.txt
playstore.egg-info/requires.txt
playstore.egg-info/top_level.txt
playstore.egg-info/zip-safe