Metadata-Version: 1.0
Name: playstore
Version: 0.1.2dev
Summary: Python library to access Android App details from Google Play Store.
Home-page: https://github.com/kracekumar/playstore
Author: Kracekumar
Author-email: me@kracekumar.com
License: BSD
Download-URL: https://github.com/kracekumar/playstore/archive/v0.1.2.tar.gz
Keywords: Android,playstore
Platform: UNKNOWN
